setup.py
zawn_workflow/__init__.py
zawn_workflow.egg-info/PKG-INFO
zawn_workflow.egg-info/SOURCES.txt
zawn_workflow.egg-info/dependency_links.txt
zawn_workflow.egg-info/requires.txt
zawn_workflow.egg-info/top_level.txt
zawn_workflow/context/__init__.py
zawn_workflow/context/base.py
zawn_workflow/context/context.py
zawn_workflow/context/identity.py
zawn_workflow/context/repository.py
zawn_workflow/context/runtime.py
zawn_workflow/context/searcher.py
zawn_workflow/data/__init__.py
zawn_workflow/data/exception.py
zawn_workflow/data/factory.py
zawn_workflow/data/state.py
zawn_workflow/role/__init__.py
zawn_workflow/role/designer.py
zawn_workflow/role/handler.py
zawn_workflow/role/initiator.py
zawn_workflow/test/__init__.py
zawn_workflow/test/test.py
zawn_workflow/test/test_identity.py
zawn_workflow/test/test_repository.py
zawn_workflow/test/test_runtime.py
zawn_workflow/test/test_searcher.py